{
  "steps": [
    {
      "feature": "robust6",
      "n": 6,
      "overall": 0.8609318705595638,
      "thermal": 0.8810111805125348,
      "grayscale": 0.36117711117711115,
      "gray_trust_rgb_R": 0.08333333333333333,
      "leakage": null
    },
    {
      "feature": "rgb_mean_conf",
      "n": 7,
      "overall": 0.8811087502350685,
      "thermal": 0.8990983102309268,
      "grayscale": 0.4228019734652012,
      "gray_trust_rgb_R": 0.14583333333333334,
      "leakage": 0.003424146665183
    },
    {
      "feature": "pos_euclidean_diff",
      "n": 8,
      "overall": 0.8904912627967935,
      "thermal": 0.9077737419581661,
      "grayscale": 0.6071933788564743,
      "gray_trust_rgb_R": 0.1875,
      "leakage": 0.0698401954808837,
      "gray_gain_ci": [
        0.043345281849335233,
        0.3672702485794188
      ]
    },
    {
      "feature": "xmodal_scale_ratio",
      "n": 9,
      "overall": 0.8929176956144508,
      "thermal": 0.9110260744007849,
      "grayscale": 0.5979811778992108,
      "gray_trust_rgb_R": 0.16666666666666666,
      "leakage": 0.0015106676372142
    },
    {
      "feature": "ir_best_dist_to_center",
      "n": 10,
      "overall": 0.8926167022348388,
      "thermal": 0.910709430726583,
      "grayscale": 0.5982502893752187,
      "gray_trust_rgb_R": 0.16666666666666666,
      "leakage": 0.0145539983266296
    },
    {
      "feature": "xmodal_centroid_dist",
      "n": 11,
      "overall": 0.8933829397328337,
      "thermal": 0.911224052610096,
      "grayscale": 0.5659834229390681,
      "gray_trust_rgb_R": 0.1875,
      "leakage": 0.5712319953184386
    },
    {
      "feature": "ir_mean_conf",
      "n": 12,
      "overall": 0.8921235129309999,
      "thermal": 0.9100762101804359,
      "grayscale": 0.559996606991696,
      "gray_trust_rgb_R": 0.1875,
      "leakage": 0.0024825814917307
    },
    {
      "feature": "conf_product",
      "n": 13,
      "overall": 0.8928409876741934,
      "thermal": 0.9108659965945135,
      "grayscale": 0.5562612007168459,
      "gray_trust_rgb_R": 0.1875,
      "leakage": 0.0030459575249624
    },
    {
      "feature": "area_diff",
      "n": 14,
      "overall": 0.888143608165419,
      "thermal": 0.9055236977789293,
      "grayscale": 0.5584925442684063,
      "gray_trust_rgb_R": 0.16666666666666666,
      "leakage": 0.1100415267179406
    }
  ],
  "winner": {
    "feature": "pos_euclidean_diff",
    "n": 8,
    "overall": 0.8904912627967935,
    "thermal": 0.9077737419581661,
    "grayscale": 0.6071933788564743,
    "gray_trust_rgb_R": 0.1875,
    "leakage": 0.0698401954808837,
    "gray_gain_ci": [
      0.043345281849335233,
      0.3672702485794188
    ]
  },
  "artifact_dropped": [
    "brightness_ratio",
    "ir_edge_density",
    "ir_img_mean",
    "ir_img_std",
    "ir_sky_ground_ratio",
    "rgb_best_local_contrast",
    "rgb_best_target_bg_delta",
    "rgb_blurriness",
    "rgb_img_mean",
    "scene_entropy_diff"
  ],
  "excluded_from_pool": [
    "rgb_best_local_contrast",
    "ir_best_local_contrast",
    "rgb_img_mean",
    "ir_img_mean",
    "rgb_img_std",
    "rgb_best_target_bg_delta",
    "ir_best_target_bg_delta",
    "rgb_n_dets",
    "ir_n_dets",
    "rgb_detected",
    "ir_detected",
    "both_detect",
    "neither_detect",
    "rgb_only_detect",
    "ir_only_detect",
    "ir_img_std",
    "rgb_img_dynamic_range",
    "ir_img_dynamic_range",
    "rgb_img_entropy",
    "ir_img_entropy",
    "rgb_sky_ground_ratio",
    "ir_sky_ground_ratio",
    "rgb_edge_density",
    "ir_edge_density",
    "rgb_blurriness",
    "ir_blurriness",
    "det_count_diff",
    "total_dets",
    "contrast_diff",
    "bg_delta_diff",
    "scene_entropy_mean",
    "scene_entropy_diff",
    "brightness_ratio"
  ]
}